mockito/__init__.py
mockito/mockito.py
mockito_test-0.3.2.dist-info/LICENSE
mockito_test-0.3.2.dist-info/METADATA
mockito_test-0.3.2.dist-info/WHEEL
mockito_test-0.3.2.dist-info/top_level.txt
mockito_test-0.3.2.dist-info/RECORD
