Metadata-Version: 2.1
Name: mockito-test
Version: 0.3.2
Summary: Package to help standardization of data used in mocks.
Author-email: Luiz Antonio Calliari Filho <luizcalliari.filho@gmail.com>
Project-URL: Homepage, https://github.com/luizcalliari/mockito-test
Project-URL: Bug Tracker, https://github.com/luizcalliari/mockito-test/issues
Project-URL: Documentation, https://github.com/luizcalliari/mockito-test/wiki
Keywords: mock,tests,unittest
Classifier: Programming Language :: Python :: 3
Classifier: License :: OSI Approved :: MIT License
Classifier: Operating System :: OS Independent
Requires-Python: >=3.7
License-File: LICENSE
Requires-Dist: mock >=5.0.0
